JustScan/__init__.py
JustScan/api/__init__.py
JustScan/api/itc_cli.py
JustScan/api/just_scan_api.py
JustScan/config/__init__.py
JustScan/config/config.py
JustScan/config/config_db.py
JustScan/config/logger.py
JustScan/config/pydantic_models.py
JustScan/database/__init__.py
JustScan/database/crud.py
JustScan/database/data_models.py
JustScan/database/database.py
JustScan/face_id/__init__.py
JustScan/face_id/commons/__init__.py
JustScan/face_id/commons/config.py
JustScan/face_id/commons/AntiSpoof/CDCN_config.py
JustScan/face_id/commons/AntiSpoof/__init__.py
JustScan/face_id/commons/AntiSpoof/anti_spoof.py
JustScan/face_id/commons/AntiSpoof/liveness_check.py
JustScan/face_id/commons/AntiSpoof/liveness_onnx_check.py
JustScan/face_id/commons/AntiSpoof/utility.py
JustScan/face_id/commons/AntiSpoof/data_io/__init__.py
JustScan/face_id/commons/AntiSpoof/data_io/functional.py
JustScan/face_id/commons/AntiSpoof/data_io/transform.py
JustScan/face_id/commons/AntiSpoof/model_lib/MiniFASNet.py
JustScan/face_id/commons/AntiSpoof/model_lib/MultiFTNet.py
JustScan/face_id/commons/AntiSpoof/model_lib/__init__.py
JustScan/face_id/commons/ArcFace/ArcFace_onnx.py
JustScan/face_id/commons/ArcFace/__init__.py
JustScan/face_id/commons/ArcFace/lib/__init__.py
JustScan/face_id/commons/ArcFace/lib/layers.py
JustScan/face_id/commons/ArcFace/lib/models.py
JustScan/face_id/commons/ArcFace/lib/utils.py
JustScan/face_id/commons/CloseEyes/__init__.py
JustScan/face_id/commons/CloseEyes/close_eyes_v2.py
JustScan/face_id/commons/CloseEyes/utils.py
JustScan/face_id/commons/FaceMask/__init__.py
JustScan/face_id/commons/FaceMask/face_mask_onnx.py
JustScan/face_id/commons/FaceQuality/__init__.py
JustScan/face_id/commons/FaceQuality/dom.py
JustScan/face_id/commons/FaceQuality/face_quality_assessment.py
JustScan/face_id/commons/ScrFd/__init__.py
JustScan/face_id/commons/ScrFd/scrfd.py
JustScan/face_id/libraries/__init__.py
JustScan/face_id/libraries/face_detection.py
JustScan/face_id/libraries/face_id.py
JustScan-1.2.6.dist-info/METADATA
JustScan-1.2.6.dist-info/WHEEL
JustScan-1.2.6.dist-info/entry_points.txt
JustScan-1.2.6.dist-info/top_level.txt
JustScan-1.2.6.dist-info/RECORD
